Workbook

Sheet RAW_DATA
A1: Age | B1: Attrition | C1: BusinessTravel | D1: DailyRate | E1: Department | F1: DistanceFromHome | G1: Education | H1: EducationField | I1: EmployeeCount | J1: EmployeeNumber | K1: EnvironmentSatisfaction | L1: Gender | M1: HourlyRate | N1: JobInvolvement | O1: JobLevel | P1: JobRole | Q1: JobSatisfaction | R1: MaritalStatus | S1: MonthlyIncome | T1: MonthlyRate | U1: NumCompaniesWorked | V1: Over18 | W1: OverTime | X1: PercentSalaryHike | Y1: PerformanceRating | Z1: RelationshipSatisfaction | AA1: StandardHours | AB1: StockOptionLevel | AC1: TotalWorkingYears | AD1: TrainingTimesLastYear | AE1: WorkLifeBalance | AF1: YearsAtCompany | AG1: YearsInCurrentRole | AH1: YearsSinceLastPromotion | AI1: YearsWithCurrManager
A2: 41 | B2: Yes | C2: Travel_Rarely | D2: 1102 | E2: Sales | F2: 1 | G2: 2 | H2: Life Sciences | I2: 1 | J2: 1 | K2: 2 | L2: Female | M2: 94 | N2: 3 | O2: 2 | P2: Sales Executive | Q2: 4 | R2: Single | S2: 5993 | T2: 19479 | U2: 8 | V2: Y | W2: Yes | X2: 11 | Y2: 3 | Z2: 1 | AA2: 80 | AB2: 0 | AC2: 8 | AD2: 0 | AE2: 1 | AF2: 6 | AG2: 4 | AH2: 0 | AI2: 5
A3: 49 | B3: No | C3: Travel_Frequently | D3: 279 | E3: Research & Development | F3: 8 | G3: 1 | H3: Life Sciences | I3: 1 | J3: 2 | K3: 3 | L3: Male | M3: 61 | N3: 2 | O3: 2 | P3: Research Scientist | Q3: 2 | R3: Married | S3: 5130 | T3: 24907 | U3: 1 | V3: Y | W3: No | X3: 23 | Y3: 4 | Z3: 4 | AA3: 80 | AB3: 1 | AC3: 10 | AD3: 3 | AE3: 3 | AF3: 10 | AG3: 7 | AH3: 1 | AI3: 7
A4: 37 | B4: Yes | C4: Travel_Rarely | D4: 1373 | E4: Research & Development | F4: 2 | G4: 2 | H4: Other | I4: 1 | J4: 4 | K4: 4 | L4: Male | M4: 92 | N4: 2 | O4: 1 | P4: Laboratory Technician | Q4: 3 | R4: Single | S4: 2090 | T4: 2396 | U4: 6 | V4: Y | W4: Yes | X4: 15 | Y4: 3 | Z4: 2 | AA4: 80 | AB4: 0 | AC4: 7 | AD4: 3 | AE4: 3 | AF4: 0 | AG4: 0 | AH4: 0 | AI4: 0
A5: 33 | B5: No | C5: Travel_Frequently | D5: 1392 | E5: Research & Development | F5: 3 | G5: 4 | H5: Life Sciences | I5: 1 | J5: 5 | K5: 4 | L5: Female | M5: 56 | N5: 3 | O5: 1 | P5: Research Scientist | Q5: 3 | R5: Married | S5: 2909 | T5: 23159 | U5: 1 | V5: Y | W5: Yes | X5: 11 | Y5: 3 | Z5: 3 | AA5: 80 | AB5: 0 | AC5: 8 | AD5: 3 | AE5: 3 | AF5: 8 | AG5: 7 | AH5: 3 | AI5: 0
A6: 27 | B6: No | C6: Travel_Rarely | D6: 591 | E6: Research & Development | F6: 2 | G6: 1 | H6: Medical | I6: 1 | J6: 7 | K6: 1 | L6: Male | M6: 40 | N6: 3 | O6: 1 | P6: Laboratory Technician | Q6: 2 | R6: Married | S6: 3468 | T6: 16632 | U6: 9 | V6: Y | W6: No | X6: 12 | Y6: 3 | Z6: 4 | AA6: 80 | AB6: 1 | AC6: 6 | AD6: 3 | AE6: 3 | AF6: 2 | AG6: 2 | AH6: 2 | AI6: 2
A7: 32 | B7: No | C7: Travel_Frequently | D7: 1005 | E7: Research & Development | F7: 2 | G7: 2 | H7: Life Sciences | I7: 1 | J7: 8 | K7: 4 | L7: Male | M7: 79 | N7: 3 | O7: 1 | P7: Laboratory Technician | Q7: 4 | R7: Single | S7: 3068 | T7: 11864 | U7: 0 | V7: Y | W7: No | X7: 13 | Y7: 3 | Z7: 3 | AA7: 80 | AB7: 0 | AC7: 8 | AD7: 2 | AE7: 2 | AF7: 7 | AG7: 7 | AH7: 3 | AI7: 6
A8: 59 | B8: No | C8: Travel_Rarely | D8: 1324 | E8: Research & Development | F8: 3 | G8: 3 | H8: Medical | I8: 1 | J8: 10 | K8: 3 | L8: Female | M8: 81 | N8: 4 | O8: 1 | P8: Laboratory Technician | Q8: 1 | R8: Married | S8: 2670 | T8: 9964 | U8: 4 | V8: Y | W8: Yes | X8: 20 | Y8: 4 | Z8: 1 | AA8: 80 | AB8: 3 | AC8: 12 | AD8: 3 | AE8: 2 | AF8: 1 | AG8: 0 | AH8: 0 | AI8: 0
A9: 30 | B9: No | C9: Travel_Rarely | D9: 1358 | E9: Research & Development | F9: 24 | G9: 1 | H9: Life Sciences | I9: 1 | J9: 11 | K9: 4 | L9: Male | M9: 67 | N9: 3 | O9: 1 | P9: Laboratory Technician | Q9: 3 | R9: Divorced | S9: 2693 | T9: 13335 | U9: 1 | V9: Y | W9: No | X9: 22 | Y9: 4 | Z9: 2 | AA9: 80 | AB9: 1 | AC9: 1 | AD9: 2 | AE9: 3 | AF9: 1 | AG9: 0 | AH9: 0 | AI9: 0
A10: 38 | B10: No | C10: Travel_Frequently | D10: 216 | E10: Research & Development | F10: 23 | G10: 3 | H10: Life Sciences | I10: 1 | J10: 12 | K10: 4 | L10: Male | M10: 44 | N10: 2 | O10: 3 | P10: Manufacturing Director | Q10: 3 | R10: Single | S10: 9526 | T10: 8787 | U10: 0 | V10: Y | W10: No | X10: 21 | Y10: 4 | Z10: 2 | AA10: 80 | AB10: 0 | AC10: 10 | AD10: 2 | AE10: 3 | AF10: 9 | AG10: 7 | AH10: 1 | AI10: 8
A11: 36 | B11: No | C11: Travel_Rarely | D11: 1299 | E11: Research & Development | F11: 27 | G11: 3 | H11: Medical | I11: 1 | J11: 13 | K11: 3 | L11: Male | M11: 94 | N11: 3 | O11: 2 | P11: Healthcare Representative | Q11: 3 | R11: Married | S11: 5237 | T11: 16577 | U11: 6 | V11: Y | W11: No | X11: 13 | Y11: 3 | Z11: 2 | AA11: 80 | AB11: 2 | AC11: 17 | AD11: 3 | AE11: 2 | AF11: 7 | AG11: 7 | AH11: 7 | AI11: 7
A12: 35 | B12: No | C12: Travel_Rarely | D12: 809 | E12: Research & Development | F12: 16 | G12: 3 | H12: Medical | I12: 1 | J12: 14 | K12: 1 | L12: Male | M12: 84 | N12: 4 | O12: 1 | P12: Laboratory Technician | Q12: 2 | R12: Married | S12: 2426 | T12: 16479 | U12: 0 | V12: Y | W12: No | X12: 13 | Y12: 3 | Z12: 3 | AA12: 80 | AB12: 1 | AC12: 6 | AD12: 5 | AE12: 3 | AF12: 5 | AG12: 4 | AH12: 0 | AI12: 3
A13: 29 | B13: No | C13: Travel_Rarely | D13: 153 | E13: Research & Development | F13: 15 | G13: 2 | H13: Life Sciences | I13: 1 | J13: 15 | K13: 4 | L13: Female | M13: 49 | N13: 2 | O13: 2 | P13: Laboratory Technician | Q13: 3 | R13: Single | S13: 4193 | T13: 12682 | U13: 0 | V13: Y | W13: Yes | X13: 12 | Y13: 3 | Z13: 4 | AA13: 80 | AB13: 0 | AC13: 10 | AD13: 3 | AE13: 3 | AF13: 9 | AG13: 5 | AH13: 0 | AI13: 8
... A1471: 34 | B1471: No | C1471: Travel_Rarely | D1471: 628 | E1471: Research & Development | F1471: 8 | G1471: 3 | H1471: Medical | I1471: 1 | J1471: 2068 | K1471: 2 | L1471: Male | M1471: 82 | N1471: 4 | O1471: 2 | P1471: Laboratory Technician | Q1471: 3 | R1471: Married | S1471: 4404 | T1471: 10228 | U1471: 2 | V1471: Y | W1471: No | X1471: 12 | Y1471: 3 | Z1471: 1 | AA1471: 80 | AB1471: 0 | AC1471: 6 | AD1471: 3 | AE1471: 4 | AF1471: 4 | AG1471: 3 | AH1471: 1 | AI1471: 2

Sheet CLEAN_DATA
A1: , | B1: Attrition | C1: BusinessTravel | D1: DailyRate | E1: Department | F1: DistanceFromHome | G1: Education | H1: EducationField | I1: EmployeeCount | J1: EmployeeNumber | K1: EnvironmentSatisfaction | L1: Gender | M1: HourlyRate | N1: JobInvolvement | O1: JobLevel | P1: JobRole | Q1: JobSatisfaction | R1: MaritalStatus | S1: MonthlyIncome | T1: MonthlyRate | U1: NumCompaniesWorked | V1: Over18 | W1: OverTime | X1: PercentSalaryHike | Y1: PerformanceRating | Z1: RelationshipSatisfaction | AA1: StandardHours | AB1: StockOptionLevel | AC1: TotalWorkingYears | AD1: TrainingTimesLastYear | AE1: WorkLifeBalance | AF1: YearsAtCompany | AG1: YearsInCurrentRole | AH1: YearsSinceLastPromotion | AI1: YearsWithCurrManager
A2: 41 | B2: Yes | C2: Travel_Rarely | D2: 1102 | E2: Sales | F2: 1 | G2: 2 | H2: Life Sciences | I2: 1 | J2: 1 | K2: 2 | L2: Female | M2: 94 | N2: 3 | O2: 2 | P2: Sales Executive | Q2: 4 | R2: Single | S2: 5993 | T2: 19479 | U2: 8 | V2: Y | W2: Yes | X2: 11 | Y2: 3 | Z2: 1 | AA2: 80 | AB2: 0 | AC2: 8 | AD2: 0 | AE2: 1 | AF2: 6 | AG2: 4 | AH2: 0 | AI2: 5
A3: 49 | B3: No | C3: Travel_Frequently | D3: 279 | E3: Research & Development | F3: 8 | G3: 1 | H3: Life Sciences | I3: 1 | J3: 2 | K3: 3 | L3: Male | M3: 61 | N3: 2 | O3: 2 | P3: Research Scientist | Q3: 2 | R3: Married | S3: 5130 | T3: 24907 | U3: 1 | V3: Y | W3: No | X3: 23 | Y3: 4 | Z3: 4 | AA3: 80 | AB3: 1 | AC3: 10 | AD3: 3 | AE3: 3 | AF3: 10 | AG3: 7 | AH3: 1 | AI3: 7
A4: 37 | B4: Yes | C4: Travel_Rarely | D4: 1373 | E4: Research & Development | F4: 2 | G4: 2 | H4: Other | I4: 1 | J4: 4 | K4: 4 | L4: Male | M4: 92 | N4: 2 | O4: 1 | P4: Laboratory Technician | Q4: 3 | R4: Single | S4: 2090 | T4: 2396 | U4: 6 | V4: Y | W4: Yes | X4: 15 | Y4: 3 | Z4: 2 | AA4: 80 | AB4: 0 | AC4: 7 | AD4: 3 | AE4: 3 | AF4: 0 | AG4: 0 | AH4: 0 | AI4: 0
A5: 33 | B5: No | C5: Travel_Frequently | D5: 1392 | E5: Research & Development | F5: 3 | G5: 4 | H5: Life Sciences | I5: 1 | J5: 5 | K5: 4 | L5: Female | M5: 56 | N5: 3 | O5: 1 | P5: Research Scientist | Q5: 3 | R5: Married | S5: 2909 | T5: 23159 | U5: 1 | V5: Y | W5: Yes | X5: 11 | Y5: 3 | Z5: 3 | AA5: 80 | AB5: 0 | AC5: 8 | AD5: 3 | AE5: 3 | AF5: 8 | AG5: 7 | AH5: 3 | AI5: 0
A6: 27 | B6: No | C6: Travel_Rarely | D6: 591 | E6: Research & Development | F6: 2 | G6: 1 | H6: Medical | I6: 1 | J6: 7 | K6: 1 | L6: Male | M6: 40 | N6: 3 | O6: 1 | P6: Laboratory Technician | Q6: 2 | R6: Married | S6: 3468 | T6: 16632 | U6: 9 | V6: Y | W6: No | X6: 12 | Y6: 3 | Z6: 4 | AA6: 80 | AB6: 1 | AC6: 6 | AD6: 3 | AE6: 3 | AF6: 2 | AG6: 2 | AH6: 2 | AI6: 2
A7: 32 | B7: No | C7: Travel_Frequently | D7: 1005 | E7: Research & Development | F7: 2 | G7: 2 | H7: Life Sciences | I7: 1 | J7: 8 | K7: 4 | L7: Male | M7: 79 | N7: 3 | O7: 1 | P7: Laboratory Technician | Q7: 4 | R7: Single | S7: 3068 | T7: 11864 | U7: 0 | V7: Y | W7: No | X7: 13 | Y7: 3 | Z7: 3 | AA7: 80 | AB7: 0 | AC7: 8 | AD7: 2 | AE7: 2 | AF7: 7 | AG7: 7 | AH7: 3 | AI7: 6
A8: 59 | B8: No | C8: Travel_Rarely | D8: 1324 | E8: Research & Development | F8: 3 | G8: 3 | H8: Medical | I8: 1 | J8: 10 | K8: 3 | L8: Female | M8: 81 | N8: 4 | O8: 1 | P8: Laboratory Technician | Q8: 1 | R8: Married | S8: 2670 | T8: 9964 | U8: 4 | V8: Y | W8: Yes | X8: 20 | Y8: 4 | Z8: 1 | AA8: 80 | AB8: 3 | AC8: 12 | AD8: 3 | AE8: 2 | AF8: 1 | AG8: 0 | AH8: 0 | AI8: 0
A9: 30 | B9: No | C9: Travel_Rarely | D9: 1358 | E9: Research & Development | F9: 24 | G9: 1 | H9: Life Sciences | I9: 1 | J9: 11 | K9: 4 | L9: Male | M9: 67 | N9: 3 | O9: 1 | P9: Laboratory Technician | Q9: 3 | R9: Divorced | S9: 2693 | T9: 13335 | U9: 1 | V9: Y | W9: No | X9: 22 | Y9: 4 | Z9: 2 | AA9: 80 | AB9: 1 | AC9: 1 | AD9: 2 | AE9: 3 | AF9: 1 | AG9: 0 | AH9: 0 | AI9: 0
A10: 38 | B10: No | C10: Travel_Frequently | D10: 216 | E10: Research & Development | F10: 23 | G10: 3 | H10: Life Sciences | I10: 1 | J10: 12 | K10: 4 | L10: Male | M10: 44 | N10: 2 | O10: 3 | P10: Manufacturing Director | Q10: 3 | R10: Single | S10: 9526 | T10: 8787 | U10: 0 | V10: Y | W10: No | X10: 21 | Y10: 4 | Z10: 2 | AA10: 80 | AB10: 0 | AC10: 10 | AD10: 2 | AE10: 3 | AF10: 9 | AG10: 7 | AH10: 1 | AI10: 8
A11: 36 | B11: No | C11: Travel_Rarely | D11: 1299 | E11: Research & Development | F11: 27 | G11: 3 | H11: Medical | I11: 1 | J11: 13 | K11: 3 | L11: Male | M11: 94 | N11: 3 | O11: 2 | P11: Healthcare Representative | Q11: 3 | R11: Married | S11: 5237 | T11: 16577 | U11: 6 | V11: Y | W11: No | X11: 13 | Y11: 3 | Z11: 2 | AA11: 80 | AB11: 2 | AC11: 17 | AD11: 3 | AE11: 2 | AF11: 7 | AG11: 7 | AH11: 7 | AI11: 7
A12: 35 | B12: No | C12: Travel_Rarely | D12: 809 | E12: Research & Development | F12: 16 | G12: 3 | H12: Medical | I12: 1 | J12: 14 | K12: 1 | L12: Male | M12: 84 | N12: 4 | O12: 1 | P12: Laboratory Technician | Q12: 2 | R12: Married | S12: 2426 | T12: 16479 | U12: 0 | V12: Y | W12: No | X12: 13 | Y12: 3 | Z12: 3 | AA12: 80 | AB12: 1 | AC12: 6 | AD12: 5 | AE12: 3 | AF12: 5 | AG12: 4 | AH12: 0 | AI12: 3
A13: 29 | B13: No | C13: Travel_Rarely | D13: 153 | E13: Research & Development | F13: 15 | G13: 2 | H13: Life Sciences | I13: 1 | J13: 15 | K13: 4 | L13: Female | M13: 49 | N13: 2 | O13: 2 | P13: Laboratory Technician | Q13: 3 | R13: Single | S13: 4193 | T13: 12682 | U13: 0 | V13: Y | W13: Yes | X13: 12 | Y13: 3 | Z13: 4 | AA13: 80 | AB13: 0 | AC13: 10 | AD13: 3 | AE13: 3 | AF13: 9 | AG13: 5 | AH13: 0 | AI13: 8
... A1471: 34 | B1471: No | C1471: Travel_Rarely | D1471: 628 | E1471: Research & Development | F1471: 8 | G1471: 3 | H1471: Medical | I1471: 1 | J1471: 2068 | K1471: 2 | L1471: Male | M1471: 82 | N1471: 4 | O1471: 2 | P1471: Laboratory Technician | Q1471: 3 | R1471: Married | S1471: 4404 | T1471: 10228 | U1471: 2 | V1471: Y | W1471: No | X1471: 12 | Y1471: 3 | Z1471: 1 | AA1471: 80 | AB1471: 0 | AC1471: 6 | AD1471: 3 | AE1471: 4 | AF1471: 4 | AG1471: 3 | AH1471: 1 | AI1471: 2

Sheet FEATURES
A1: EMPLOYEE NUMBER | B1: ATTRITION | C1: AGE | D1: DEPARTMENT | E1: JOBROLE | F1: MONTHLY INCOME | G1: OVERTIME | H1: YEARS AT COMPANY | I1: YEAR SINCE LAST PROMOTION | J1: JOB SATISFACTION | K1: WORK LIFE BALANCE | L1: HIGH ATTRITION RISK | M1: INCOME LEVEL GROUP | N1: EXPERIENCE LEVEL | O1: PROMOTION STAGNATION | P1: WORK PRESSURE LEVEL | Q1: ENGAGEMENT LEVEL | R1: RETENTION PROIRITY
A2: 1 | B2: Yes | C2: 41 | D2: Sales | E2: Sales Executive | F2: 5993 | G2: Yes | H2: 6 | I2: 0 | J2: 4 | K2: 1 | L2: =IF(AND(G2="YES",J2<=2,I2>=3),"HIGH RISK","NORMAL") -> NORMAL | M2: =IF(F2<=4000,"LOW",IF(F2>9000,"MEDIUM","HIGH")) -> HIGH | N2: =IF(H2<=2,"NEW",IF(H2<=6,"MID","SENIOR")) -> MID | O2: =IF(I2<=1,"RECENTLY PROMOTED",IF(I2<=3,"MODERATE-WAIT","STAGNANT")) -> RECENTLY PROMOTED | P2: =IF(AND(G2="Yes",K2<=2),"High_Pressure", IF(OR(G2="Yes",K2=3),"Medium_Pressure", "Low_Pressure")) -> High_Pressure | Q2: =IF(AND(J2>=3,K2>=3,L2>=3), "HIGHLY_ENGAGED", IF(OR(J2<=2,K2<=2,L2<=2), "DISENGAGED", "MODERATELY_ENGAGED")) -> DISENGAGED | R2: =IF(AND(L2="HIGH",O2="STAGNANT",P2="HIGH_PRESSURE",Q2="DISENGAGED"), "CRITICAL", IF(AND(L2="HIGH",M2="LOW",P2="HIGH_PRESSURE",Q2="MODERATELY_ENGAGED"), "HIGH", IF(AND(L2="NORMAL",M2="MEDIUM",O2="MODERATE-WAIT",P2="MEDIUM_PRESSURE",Q2="MODERATELY_ENGAGED"), "MEDIUM", "LOW"))) -> LOW
A3: 2 | B3: No | C3: 49 | D3: Research & Development | E3: Research Scientist | F3: 5130 | G3: No | H3: 10 | I3: 1 | J3: 2 | K3: 3 | L3: =IF(AND(G3="YES",J3<=2,I3>=3),"HIGH RISK","NORMAL") -> NORMAL | M3: =IF(F3<=4000,"LOW",IF(F3>9000,"MEDIUM","HIGH")) -> HIGH | N3: =IF(H3<=2,"NEW",IF(H3<=6,"MID","SENIOR")) -> SENIOR | O3: =IF(I3<=1,"RECENTLY PROMOTED",IF(I3<=3,"MODERATE-WAIT","STAGNANT")) -> RECENTLY PROMOTED | P3: =IF(AND(G3="Yes",K3<=2),"High_Pressure", IF(OR(G3="Yes",K3=3),"Medium_Pressure", "Low_Pressure")) -> Medium_Pressure | Q3: =IF(AND(J3>=3,K3>=3,L3>=3), "HIGHLY_ENGAGED", IF(OR(J3<=2,K3<=2,L3<=2), "DISENGAGED", "MODERATELY_ENGAGED")) -> DISENGAGED | R3: =IF(AND(L3="HIGH",O3="STAGNANT",P3="HIGH_PRESSURE",Q3="DISENGAGED"), "CRITICAL", IF(AND(L3="HIGH",M3="LOW",P3="HIGH_PRESSURE",Q3="MODERATELY_ENGAGED"), "HIGH", IF(AND(L3="NORMAL",M3="MEDIUM",O3="MODERATE-WAIT",P3="MEDIUM_PRESSURE",Q3="MODERATELY_ENGAGED"), "MEDIUM", "LOW"))) -> LOW
A4: 4 | B4: Yes | C4: 37 | D4: Research & Development | E4: Laboratory Technician | F4: 2090 | G4: Yes | H4: 0 | I4: 0 | J4: 3 | K4: 3 | L4: =IF(AND(G4="YES",J4<=2,I4>=3),"HIGH RISK","NORMAL") -> NORMAL | M4: =IF(F4<=4000,"LOW",IF(F4>9000,"MEDIUM","HIGH")) -> LOW | N4: =IF(H4<=2,"NEW",IF(H4<=6,"MID","SENIOR")) -> NEW | O4: =IF(I4<=1,"RECENTLY PROMOTED",IF(I4<=3,"MODERATE-WAIT","STAGNANT")) -> RECENTLY PROMOTED | P4: =IF(AND(G4="Yes",K4<=2),"High_Pressure", IF(OR(G4="Yes",K4=3),"Medium_Pressure", "Low_Pressure")) -> Medium_Pressure | Q4: =IF(AND(J4>=3,K4>=3,L4>=3), "HIGHLY_ENGAGED", IF(OR(J4<=2,K4<=2,L4<=2), "DISENGAGED", "MODERATELY_ENGAGED")) -> HIGHLY_ENGAGED | R4: =IF(AND(L4="HIGH",O4="STAGNANT",P4="HIGH_PRESSURE",Q4="DISENGAGED"), "CRITICAL", IF(AND(L4="HIGH",M4="LOW",P4="HIGH_PRESSURE",Q4="MODERATELY_ENGAGED"), "HIGH", IF(AND(L4="NORMAL",M4="MEDIUM",O4="MODERATE-WAIT",P4="MEDIUM_PRESSURE",Q4="MODERATELY_ENGAGED"), "MEDIUM", "LOW"))) -> LOW
A5: 5 | B5: No | C5: 33 | D5: Research & Development | E5: Research Scientist | F5: 2909 | G5: Yes | H5: 8 | I5: 3 | J5: 3 | K5: 3 | L5: =IF(AND(G5="YES",J5<=2,I5>=3),"HIGH RISK","NORMAL") -> NORMAL | M5: =IF(F5<=4000,"LOW",IF(F5>9000,"MEDIUM","HIGH")) -> LOW | N5: =IF(H5<=2,"NEW",IF(H5<=6,"MID","SENIOR")) -> SENIOR | O5: =IF(I5<=1,"RECENTLY PROMOTED",IF(I5<=3,"MODERATE-WAIT","STAGNANT")) -> MODERATE-WAIT | P5: =IF(AND(G5="Yes",K5<=2),"High_Pressure", IF(OR(G5="Yes",K5=3),"Medium_Pressure", "Low_Pressure")) -> Medium_Pressure | Q5: =IF(AND(J5>=3,K5>=3,L5>=3), "HIGHLY_ENGAGED", IF(OR(J5<=2,K5<=2,L5<=2), "DISENGAGED", "MODERATELY_ENGAGED")) -> HIGHLY_ENGAGED | R5: =IF(AND(L5="HIGH",O5="STAGNANT",P5="HIGH_PRESSURE",Q5="DISENGAGED"), "CRITICAL", IF(AND(L5="HIGH",M5="LOW",P5="HIGH_PRESSURE",Q5="MODERATELY_ENGAGED"), "HIGH", IF(AND(L5="NORMAL",M5="MEDIUM",O5="MODERATE-WAIT",P5="MEDIUM_PRESSURE",Q5="MODERATELY_ENGAGED"), "MEDIUM", "LOW"))) -> LOW
A6: 7 | B6: No | C6: 27 | D6: Research & Development | E6: Laboratory Technician | F6: 3468 | G6: No | H6: 2 | I6: 2 | J6: 2 | K6: 3 | L6: =IF(AND(G6="YES",J6<=2,I6>=3),"HIGH RISK","NORMAL") -> NORMAL | M6: =IF(F6<=4000,"LOW",IF(F6>9000,"MEDIUM","HIGH")) -> LOW | N6: =IF(H6<=2,"NEW",IF(H6<=6,"MID","SENIOR")) -> NEW | O6: =IF(I6<=1,"RECENTLY PROMOTED",IF(I6<=3,"MODERATE-WAIT","STAGNANT")) -> MODERATE-WAIT | P6: =IF(AND(G6="Yes",K6<=2),"High_Pressure", IF(OR(G6="Yes",K6=3),"Medium_Pressure", "Low_Pressure")) -> Medium_Pressure | Q6: =IF(AND(J6>=3,K6>=3,L6>=3), "HIGHLY_ENGAGED", IF(OR(J6<=2,K6<=2,L6<=2), "DISENGAGED", "MODERATELY_ENGAGED")) -> DISENGAGED | R6: =IF(AND(L6="HIGH",O6="STAGNANT",P6="HIGH_PRESSURE",Q6="DISENGAGED"), "CRITICAL", IF(AND(L6="HIGH",M6="LOW",P6="HIGH_PRESSURE",Q6="MODERATELY_ENGAGED"), "HIGH", IF(AND(L6="NORMAL",M6="MEDIUM",O6="MODERATE-WAIT",P6="MEDIUM_PRESSURE",Q6="MODERATELY_ENGAGED"), "MEDIUM", "LOW"))) -> LOW
A7: 8 | B7: No | C7: 32 | D7: Research & Development | E7: Laboratory Technician | F7: 3068 | G7: No | H7: 7 | I7: 3 | J7: 4 | K7: 2 | L7: =IF(AND(G7="YES",J7<=2,I7>=3),"HIGH RISK","NORMAL") -> NORMAL | M7: =IF(F7<=4000,"LOW",IF(F7>9000,"MEDIUM","HIGH")) -> LOW | N7: =IF(H7<=2,"NEW",IF(H7<=6,"MID","SENIOR")) -> SENIOR | O7: =IF(I7<=1,"RECENTLY PROMOTED",IF(I7<=3,"MODERATE-WAIT","STAGNANT")) -> MODERATE-WAIT | P7: =IF(AND(G7="Yes",K7<=2),"High_Pressure", IF(OR(G7="Yes",K7=3),"Medium_Pressure", "Low_Pressure")) -> Low_Pressure | Q7: =IF(AND(J7>=3,K7>=3,L7>=3), "HIGHLY_ENGAGED", IF(OR(J7<=2,K7<=2,L7<=2), "DISENGAGED", "MODERATELY_ENGAGED")) -> DISENGAGED | R7: =IF(AND(L7="HIGH",O7="STAGNANT",P7="HIGH_PRESSURE",Q7="DISENGAGED"), "CRITICAL", IF(AND(L7="HIGH",M7="LOW",P7="HIGH_PRESSURE",Q7="MODERATELY_ENGAGED"), "HIGH", IF(AND(L7="NORMAL",M7="MEDIUM",O7="MODERATE-WAIT",P7="MEDIUM_PRESSURE",Q7="MODERATELY_ENGAGED"), "MEDIUM", "LOW"))) -> LOW
A8: 10 | B8: No | C8: 59 | D8: Research & Development | E8: Laboratory Technician | F8: 2670 | G8: Yes | H8: 1 | I8: 0 | J8: 1 | K8: 2 | L8: =IF(AND(G8="YES",J8<=2,I8>=3),"HIGH RISK","NORMAL") -> NORMAL | M8: =IF(F8<=4000,"LOW",IF(F8>9000,"MEDIUM","HIGH")) -> LOW | N8: =IF(H8<=2,"NEW",IF(H8<=6,"MID","SENIOR")) -> NEW | O8: =IF(I8<=1,"RECENTLY PROMOTED",IF(I8<=3,"MODERATE-WAIT","STAGNANT")) -> RECENTLY PROMOTED | P8: =IF(AND(G8="Yes",K8<=2),"High_Pressure", IF(OR(G8="Yes",K8=3),"Medium_Pressure", "Low_Pressure")) -> High_Pressure | Q8: =IF(AND(J8>=3,K8>=3,L8>=3), "HIGHLY_ENGAGED", IF(OR(J8<=2,K8<=2,L8<=2), "DISENGAGED", "MODERATELY_ENGAGED")) -> DISENGAGED | R8: =IF(AND(L8="HIGH",O8="STAGNANT",P8="HIGH_PRESSURE",Q8="DISENGAGED"), "CRITICAL", IF(AND(L8="HIGH",M8="LOW",P8="HIGH_PRESSURE",Q8="MODERATELY_ENGAGED"), "HIGH", IF(AND(L8="NORMAL",M8="MEDIUM",O8="MODERATE-WAIT",P8="MEDIUM_PRESSURE",Q8="MODERATELY_ENGAGED"), "MEDIUM", "LOW"))) -> LOW
A9: 11 | B9: No | C9: 30 | D9: Research & Development | E9: Laboratory Technician | F9: 2693 | G9: No | H9: 1 | I9: 0 | J9: 3 | K9: 3 | L9: =IF(AND(G9="YES",J9<=2,I9>=3),"HIGH RISK","NORMAL") -> NORMAL | M9: =IF(F9<=4000,"LOW",IF(F9>9000,"MEDIUM","HIGH")) -> LOW | N9: =IF(H9<=2,"NEW",IF(H9<=6,"MID","SENIOR")) -> NEW | O9: =IF(I9<=1,"RECENTLY PROMOTED",IF(I9<=3,"MODERATE-WAIT","STAGNANT")) -> RECENTLY PROMOTED | P9: =IF(AND(G9="Yes",K9<=2),"High_Pressure", IF(OR(G9="Yes",K9=3),"Medium_Pressure", "Low_Pressure")) -> Medium_Pressure | Q9: =IF(AND(J9>=3,K9>=3,L9>=3), "HIGHLY_ENGAGED", IF(OR(J9<=2,K9<=2,L9<=2), "DISENGAGED", "MODERATELY_ENGAGED")) -> HIGHLY_ENGAGED | R9: =IF(AND(L9="HIGH",O9="STAGNANT",P9="HIGH_PRESSURE",Q9="DISENGAGED"), "CRITICAL", IF(AND(L9="HIGH",M9="LOW",P9="HIGH_PRESSURE",Q9="MODERATELY_ENGAGED"), "HIGH", IF(AND(L9="NORMAL",M9="MEDIUM",O9="MODERATE-WAIT",P9="MEDIUM_PRESSURE",Q9="MODERATELY_ENGAGED"), "MEDIUM", "LOW"))) -> LOW
A10: 12 | B10: No | C10: 38 | D10: Research & Development | E10: Manufacturing Director | F10: 9526 | G10: No | H10: 9 | I10: 1 | J10: 3 | K10: 3 | L10: =IF(AND(G10="YES",J10<=2,I10>=3),"HIGH RISK","NORMAL") -> NORMAL | M10: =IF(F10<=4000,"LOW",IF(F10>9000,"MEDIUM","HIGH")) -> MEDIUM | N10: =IF(H10<=2,"NEW",IF(H10<=6,"MID","SENIOR")) -> SENIOR | O10: =IF(I10<=1,"RECENTLY PROMOTED",IF(I10<=3,"MODERATE-WAIT","STAGNANT")) -> RECENTLY PROMOTED | P10: =IF(AND(G10="Yes",K10<=2),"High_Pressure", IF(OR(G10="Yes",K10=3),"Medium_Pressure", "Low_Pressure")) -> Medium_Pressure | Q10: =IF(AND(J10>=3,K10>=3,L10>=3), "HIGHLY_ENGAGED", IF(OR(J10<=2,K10<=2,L10<=2), "DISENGAGED", "MODERATELY_ENGAGED")) -> HIGHLY_ENGAGED | R10: =IF(AND(L10="HIGH",O10="STAGNANT",P10="HIGH_PRESSURE",Q10="DISENGAGED"), "CRITICAL", IF(AND(L10="HIGH",M10="LOW",P10="HIGH_PRESSURE",Q10="MODERATELY_ENGAGED"), "HIGH", IF(AND(L10="NORMAL",M10="MEDIUM",O10="MODERATE-WAIT",P10="MEDIUM_PRESSURE",Q10="MODERATELY_ENGAGED"), "MEDIUM", "LOW"))) -> LOW
A11: 13 | B11: No | C11: 36 | D11: Research & Development | E11: Healthcare Representative | F11: 5237 | G11: No | H11: 7 | I11: 7 | J11: 3 | K11: 2 | L11: =IF(AND(G11="YES",J11<=2,I11>=3),"HIGH RISK","NORMAL") -> NORMAL | M11: =IF(F11<=4000,"LOW",IF(F11>9000,"MEDIUM","HIGH")) -> HIGH | N11: =IF(H11<=2,"NEW",IF(H11<=6,"MID","SENIOR")) -> SENIOR | O11: =IF(I11<=1,"RECENTLY PROMOTED",IF(I11<=3,"MODERATE-WAIT","STAGNANT")) -> STAGNANT | P11: =IF(AND(G11="Yes",K11<=2),"High_Pressure", IF(OR(G11="Yes",K11=3),"Medium_Pressure", "Low_Pressure")) -> Low_Pressure | Q11: =IF(AND(J11>=3,K11>=3,L11>=3), "HIGHLY_ENGAGED", IF(OR(J11<=2,K11<=2,L11<=2), "DISENGAGED", "MODERATELY_ENGAGED")) -> DISENGAGED | R11: =IF(AND(L11="HIGH",O11="STAGNANT",P11="HIGH_PRESSURE",Q11="DISENGAGED"), "CRITICAL", IF(AND(L11="HIGH",M11="LOW",P11="HIGH_PRESSURE",Q11="MODERATELY_ENGAGED"), "HIGH", IF(AND(L11="NORMAL",M11="MEDIUM",O11="MODERATE-WAIT",P11="MEDIUM_PRESSURE",Q11="MODERATELY_ENGAGED"), "MEDIUM", "LOW"))) -> LOW
A12: 14 | B12: No | C12: 35 | D12: Research & Development | E12: Laboratory Technician | F12: 2426 | G12: No | H12: 5 | I12: 0 | J12: 2 | K12: 3 | L12: =IF(AND(G12="YES",J12<=2,I12>=3),"HIGH RISK","NORMAL") -> NORMAL | M12: =IF(F12<=4000,"LOW",IF(F12>9000,"MEDIUM","HIGH")) -> LOW | N12: =IF(H12<=2,"NEW",IF(H12<=6,"MID","SENIOR")) -> MID | O12: =IF(I12<=1,"RECENTLY PROMOTED",IF(I12<=3,"MODERATE-WAIT","STAGNANT")) -> RECENTLY PROMOTED | P12: =IF(AND(G12="Yes",K12<=2),"High_Pressure", IF(OR(G12="Yes",K12=3),"Medium_Pressure", "Low_Pressure")) -> Medium_Pressure | Q12: =IF(AND(J12>=3,K12>=3,L12>=3), "HIGHLY_ENGAGED", IF(OR(J12<=2,K12<=2,L12<=2), "DISENGAGED", "MODERATELY_ENGAGED")) -> DISENGAGED | R12: =IF(AND(L12="HIGH",O12="STAGNANT",P12="HIGH_PRESSURE",Q12="DISENGAGED"), "CRITICAL", IF(AND(L12="HIGH",M12="LOW",P12="HIGH_PRESSURE",Q12="MODERATELY_ENGAGED"), "HIGH", IF(AND(L12="NORMAL",M12="MEDIUM",O12="MODERATE-WAIT",P12="MEDIUM_PRESSURE",Q12="MODERATELY_ENGAGED"), "MEDIUM", "LOW"))) -> LOW
A13: 15 | B13: No | C13: 29 | D13: Research & Development | E13: Laboratory Technician | F13: 4193 | G13: Yes | H13: 9 | I13: 0 | J13: 3 | K13: 3 | L13: =IF(AND(G13="YES",J13<=2,I13>=3),"HIGH RISK","NORMAL") -> NORMAL | M13: =IF(F13<=4000,"LOW",IF(F13>9000,"MEDIUM","HIGH")) -> HIGH | N13: =IF(H13<=2,"NEW",IF(H13<=6,"MID","SENIOR")) -> SENIOR | O13: =IF(I13<=1,"RECENTLY PROMOTED",IF(I13<=3,"MODERATE-WAIT","STAGNANT")) -> RECENTLY PROMOTED | P13: =IF(AND(G13="Yes",K13<=2),"High_Pressure", IF(OR(G13="Yes",K13=3),"Medium_Pressure", "Low_Pressure")) -> Medium_Pressure | Q13: =IF(AND(J13>=3,K13>=3,L13>=3), "HIGHLY_ENGAGED", IF(OR(J13<=2,K13<=2,L13<=2), "DISENGAGED", "MODERATELY_ENGAGED")) -> HIGHLY_ENGAGED | R13: =IF(AND(L13="HIGH",O13="STAGNANT",P13="HIGH_PRESSURE",Q13="DISENGAGED"), "CRITICAL", IF(AND(L13="HIGH",M13="LOW",P13="HIGH_PRESSURE",Q13="MODERATELY_ENGAGED"), "HIGH", IF(AND(L13="NORMAL",M13="MEDIUM",O13="MODERATE-WAIT",P13="MEDIUM_PRESSURE",Q13="MODERATELY_ENGAGED"), "MEDIUM", "LOW"))) -> LOW
... A73: 94 | B73: No | C73: 29 | D73: Research & Development | E73: Research Scientist | F73: 2703 | G73: No | H73: 5 | I73: 0 | J73: 2 | K73: 3 | L73: =IF(AND(G73="YES",J73<=2,I73>=3),"HIGH RISK","NORMAL") -> NORMAL | M73: =IF(F73<=4000,"LOW",IF(F73>9000,"MEDIUM","HIGH")) -> LOW | N73: =IF(H73<=2,"NEW",IF(H73<=6,"MID","SENIOR")) -> MID | O73: =IF(I73<=1,"RECENTLY PROMOTED",IF(I73<=3,"MODERATE-WAIT","STAGNANT")) -> RECENTLY PROMOTED | P73: =IF(AND(G73="Yes",K73<=2),"High_Pressure", IF(OR(G73="Yes",K73=3),"Medium_Pressure", "Low_Pressure")) -> Medium_Pressure | Q73: =IF(AND(J73>=3,K73>=3,L73>=3), "HIGHLY_ENGAGED", IF(OR(J73<=2,K73<=2,L73<=2), "DISENGAGED", "MODERATELY_ENGAGED")) -> DISENGAGED | R73: =IF(AND(L73="HIGH",O73="STAGNANT",P73="HIGH_PRESSURE",Q73="DISENGAGED"), "CRITICAL", IF(AND(L73="HIGH",M73="LOW",P73="HIGH_PRESSURE",Q73="MODERATELY_ENGAGED"), "HIGH", IF(AND(L73="NORMAL",M73="MEDIUM",O73="MODERATE-WAIT",P73="MEDIUM_PRESSURE",Q73="MODERATELY_ENGAGED"), "MEDIUM", "LOW"))) -> LOW
A74: 95 | B74: No | C74: 31 | D74: Research & Development | E74: Research Scientist | F74: 2501 | G74: No | H74: 1 | I74: 1 | J74: 2 | K74: 3 | L74: =IF(AND(G74="YES",J74<=2,I74>=3),"HIGH RISK","NORMAL") -> NORMAL | M74: =IF(F74<=4000,"LOW",IF(F74>9000,"MEDIUM","HIGH")) -> LOW | N74: =IF(H74<=2,"NEW",IF(H74<=6,"MID","SENIOR")) -> NEW | O74: =IF(I74<=1,"RECENTLY PROMOTED",IF(I74<=3,"MODERATE-WAIT","STAGNANT")) -> RECENTLY PROMOTED | P74: =IF(AND(G74="Yes",K74<=2),"High_Pressure", IF(OR(G74="Yes",K74=3),"Medium_Pressure", "Low_Pressure")) -> Medium_Pressure | Q74: =IF(AND(J74>=3,K74>=3,L74>=3), "HIGHLY_ENGAGED", IF(OR(J74<=2,K74<=2,L74<=2), "DISENGAGED", "MODERATELY_ENGAGED")) -> DISENGAGED | R74: =IF(AND(L74="HIGH RISK",M2="LOW",O74="STAGNANT",P74="HIGH_PRESSURE",Q74="DISENGAGED"), "CRITICAL", IF(AND(L74="HIGH RISK",M74="LOW",O2="MODERATE-WAIT",P74="HIGH_PRESSURE",Q74="MODERATELY_ENGAGED"), "HIGH", IF(AND(L74="NORMAL",M74="MEDIUM",O74="MODERATE-WAIT",P74="MEDIUM_PRESSURE",Q74="MODERATELY_ENGAGED"), "MEDIUM", "LOW"))) -> LOW
A75: 96 | B75: No | C75: 32 | D75: Research & Development | E75: Research Scientist | F75: 6220 | G75: No | H75: 10 | I75: 0 | J75: 2 | K75: 3 | L75: =IF(AND(G75="YES",J75<=2,I75>=3),"HIGH RISK","NORMAL") -> NORMAL | M75: =IF(F75<=4000,"LOW",IF(F75>9000,"MEDIUM","HIGH")) -> HIGH | N75: =IF(H75<=2,"NEW",IF(H75<=6,"MID","SENIOR")) -> SENIOR | O75: =IF(I75<=1,"RECENTLY PROMOTED",IF(I75<=3,"MODERATE-WAIT","STAGNANT")) -> RECENTLY PROMOTED | P75: =IF(AND(G75="Yes",K75<=2),"High_Pressure", IF(OR(G75="Yes",K75=3),"Medium_Pressure", "Low_Pressure")) -> Medium_Pressure | Q75: =IF(AND(J75>=3,K75>=3,L75>=3), "HIGHLY_ENGAGED", IF(OR(J75<=2,K75<=2,L75<=2), "DISENGAGED", "MODERATELY_ENGAGED")) -> DISENGAGED | R75: =IF(AND(L75="HIGH",O75="STAGNANT",P75="HIGH_PRESSURE",Q75="DISENGAGED"), "CRITICAL", IF(AND(L75="HIGH",M75="LOW",P75="HIGH_PRESSURE",Q75="MODERATELY_ENGAGED"), "HIGH", IF(AND(L75="NORMAL",M75="MEDIUM",O75="MODERATE-WAIT",P75="MEDIUM_PRESSURE",Q75="MODERATELY_ENGAGED"), "MEDIUM", "LOW"))) -> LOW
A76: 97 | B76: No | C76: 36 | D76: Research & Development | E76: Laboratory Technician | F76: 3038 | G76: No | H76: 1 | I76: 0 | J76: 4 | K76: 3 | L76: =IF(AND(G76="YES",J76<=2,I76>=3),"HIGH RISK","NORMAL") -> NORMAL | M76: =IF(F76<=4000,"LOW",IF(F76>9000,"MEDIUM","HIGH")) -> LOW | N76: =IF(H76<=2,"NEW",IF(H76<=6,"MID","SENIOR")) -> NEW | O76: =IF(I76<=1,"RECENTLY PROMOTED",IF(I76<=3,"MODERATE-WAIT","STAGNANT")) -> RECENTLY PROMOTED | P76: =IF(AND(G76="Yes",K76<=2),"High_Pressure", IF(OR(G76="Yes",K76=3),"Medium_Pressure", "Low_Pressure")) -> Medium_Pressure | Q76: =IF(AND(J76>=3,K76>=3,L76>=3), "HIGHLY_ENGAGED", IF(OR(J76<=2,K76<=2,L76<=2), "DISENGAGED", "MODERATELY_ENGAGED")) -> HIGHLY_ENGAGED | R76: =IF(AND(L76="HIGH",O76="STAGNANT",P76="HIGH_PRESSURE",Q76="DISENGAGED"), "CRITICAL", IF(AND(L76="HIGH",M76="LOW",P76="HIGH_PRESSURE",Q76="MODERATELY_ENGAGED"), "HIGH", IF(AND(L76="NORMAL",M76="MEDIUM",O76="MODERATE-WAIT",P76="MEDIUM_PRESSURE",Q76="MODERATELY_ENGAGED"), "MEDIUM", "LOW"))) -> LOW
A77: 98 | B77: No | C77: 31 | D77: Research & Development | E77: Manufacturing Director | F77: 4424 | G77: No | H77: 11 | I77: 1 | J77: 4 | K77: 3 | L77: =IF(AND(G77="YES",J77<=2,I77>=3),"HIGH RISK","NORMAL") -> NORMAL | M77: =IF(F77<=4000,"LOW",IF(F77>9000,"MEDIUM","HIGH")) -> HIGH | N77: =IF(H77<=2,"NEW",IF(H77<=6,"MID","SENIOR")) -> SENIOR | O77: =IF(I77<=1,"RECENTLY PROMOTED",IF(I77<=3,"MODERATE-WAIT","STAGNANT")) -> RECENTLY PROMOTED | P77: =IF(AND(G77="Yes",K77<=2),"High_Pressure", IF(OR(G77="Yes",K77=3),"Medium_Pressure", "Low_Pressure")) -> Medium_Pressure | Q77: =IF(AND(J77>=3,K77>=3,L77>=3), "HIGHLY_ENGAGED", IF(OR(J77<=2,K77<=2,L77<=2), "DISENGAGED", "MODERATELY_ENGAGED")) -> HIGHLY_ENGAGED | R77: =IF(AND(L77="HIGH",O77="STAGNANT",P77="HIGH_PRESSURE",Q77="DISENGAGED"), "CRITICAL", IF(AND(L77="HIGH",M77="LOW",P77="HIGH_PRESSURE",Q77="MODERATELY_ENGAGED"), "HIGH", IF(AND(L77="NORMAL",M77="MEDIUM",O77="MODERATE-WAIT",P77="MEDIUM_PRESSURE",Q77="MODERATELY_ENGAGED"), "MEDIUM", "LOW"))) -> LOW
A78: 100 | B78: No | C78: 35 | D78: Sales | E78: Sales Executive | F78: 4312 | G78: No | H78: 15 | I78: 2 | J78: 1 | K78: 3 | L78: =IF(AND(G78="YES",J78<=2,I78>=3),"HIGH RISK","NORMAL") -> NORMAL | M78: =IF(F78<=4000,"LOW",IF(F78>9000,"MEDIUM","HIGH")) -> HIGH | N78: =IF(H78<=2,"NEW",IF(H78<=6,"MID","SENIOR")) -> SENIOR | O78: =IF(I78<=1,"RECENTLY PROMOTED",IF(I78<=3,"MODERATE-WAIT","STAGNANT")) -> MODERATE-WAIT | P78: =IF(AND(G78="Yes",K78<=2),"High_Pressure", IF(OR(G78="Yes",K78=3),"Medium_Pressure", "Low_Pressure")) -> Medium_Pressure | Q78: =IF(AND(J78>=3,K78>=3,L78>=3), "HIGHLY_ENGAGED", IF(OR(J78<=2,K78<=2,L78<=2), "DISENGAGED", "MODERATELY_ENGAGED")) -> DISENGAGED | R78: =IF(AND(L78="HIGH",O78="STAGNANT",P78="HIGH_PRESSURE",Q78="DISENGAGED"), "CRITICAL", IF(AND(L78="HIGH",M78="LOW",P78="HIGH_PRESSURE",Q78="MODERATELY_ENGAGED"), "HIGH", IF(AND(L78="NORMAL",M78="MEDIUM",O78="MODERATE-WAIT",P78="MEDIUM_PRESSURE",Q78="MODERATELY_ENGAGED"), "MEDIUM", "LOW"))) -> LOW
A79: 101 | B79: No | C79: 45 | D79: Research & Development | E79: Research Director | F79: 13245 | G79: Yes | H79: 0 | I79: 0 | J79: 1 | K79: 4 | L79: =IF(AND(G79="YES",J79<=2,I79>=3),"HIGH RISK","NORMAL") -> NORMAL | M79: =IF(F79<=4000,"LOW",IF(F79>9000,"MEDIUM","HIGH")) -> MEDIUM | N79: =IF(H79<=2,"NEW",IF(H79<=6,"MID","SENIOR")) -> NEW | O79: =IF(I79<=1,"RECENTLY PROMOTED",IF(I79<=3,"MODERATE-WAIT","STAGNANT")) -> RECENTLY PROMOTED | P79: =IF(AND(G79="Yes",K79<=2),"High_Pressure", IF(OR(G79="Yes",K79=3),"Medium_Pressure", "Low_Pressure")) -> Medium_Pressure | Q79: =IF(AND(J79>=3,K79>=3,L79>=3), "HIGHLY_ENGAGED", IF(OR(J79<=2,K79<=2,L79<=2), "DISENGAGED", "MODERATELY_ENGAGED")) -> DISENGAGED | R79: =IF(AND(L79="HIGH",O79="STAGNANT",P79="HIGH_PRESSURE",Q79="DISENGAGED"), "CRITICAL", IF(AND(L79="HIGH",M79="LOW",P79="HIGH_PRESSURE",Q79="MODERATELY_ENGAGED"), "HIGH", IF(AND(L79="NORMAL",M79="MEDIUM",O79="MODERATE-WAIT",P79="MEDIUM_PRESSURE",Q79="MODERATELY_ENGAGED"), "MEDIUM", "LOW"))) -> LOW
A80: 102 | B80: No | C80: 37 | D80: Research & Development | E80: Research Director | F80: 13664 | G80: No | H80: 5 | I80: 0 | J80: 3 | K80: 4 | L80: =IF(AND(G80="YES",J80<=2,I80>=3),"HIGH RISK","NORMAL") -> NORMAL | M80: =IF(F80<=4000,"LOW",IF(F80>9000,"MEDIUM","HIGH")) -> MEDIUM | N80: =IF(H80<=2,"NEW",IF(H80<=6,"MID","SENIOR")) -> MID | O80: =IF(I80<=1,"RECENTLY PROMOTED",IF(I80<=3,"MODERATE-WAIT","STAGNANT")) -> RECENTLY PROMOTED | P80: =IF(AND(G80="Yes",K80<=2),"High_Pressure", IF(OR(G80="Yes",K80=3),"Medium_Pressure", "Low_Pressure")) -> Low_Pressure | Q80: =IF(AND(J80>=3,K80>=3,L80>=3), "HIGHLY_ENGAGED", IF(OR(J80<=2,K80<=2,L80<=2), "DISENGAGED", "MODERATELY_ENGAGED")) -> HIGHLY_ENGAGED | R80: =IF(AND(L80="HIGH",O80="STAGNANT",P80="HIGH_PRESSURE",Q80="DISENGAGED"), "CRITICAL", IF(AND(L80="HIGH",M80="LOW",P80="HIGH_PRESSURE",Q80="MODERATELY_ENGAGED"), "HIGH", IF(AND(L80="NORMAL",M80="MEDIUM",O80="MODERATE-WAIT",P80="MEDIUM_PRESSURE",Q80="MODERATELY_ENGAGED"), "MEDIUM", "LOW"))) -> LOW
A81: 103 | B81: No | C81: 46 | D81: Human Resources | E81: Human Resources | F81: 5021 | G81: Yes | H81: 4 | I81: 0 | J81: 2 | K81: 3 | L81: =IF(AND(G81="YES",J81<=2,I81>=3),"HIGH RISK","NORMAL") -> NORMAL | M81: =IF(F81<=4000,"LOW",IF(F81>9000,"MEDIUM","HIGH")) -> HIGH | N81: =IF(H81<=2,"NEW",IF(H81<=6,"MID","SENIOR")) -> MID | O81: =IF(I81<=1,"RECENTLY PROMOTED",IF(I81<=3,"MODERATE-WAIT","STAGNANT")) -> RECENTLY PROMOTED | P81: =IF(AND(G81="Yes",K81<=2),"High_Pressure", IF(OR(G81="Yes",K81=3),"Medium_Pressure", "Low_Pressure")) -> Medium_Pressure | Q81: =IF(AND(J81>=3,K81>=3,L81>=3), "HIGHLY_ENGAGED", IF(OR(J81<=2,K81<=2,L81<=2), "DISENGAGED", "MODERATELY_ENGAGED")) -> DISENGAGED | R81: =IF(AND(L81="HIGH",O81="STAGNANT",P81="HIGH_PRESSURE",Q81="DISENGAGED"), "CRITICAL", IF(AND(L81="HIGH",M81="LOW",P81="HIGH_PRESSURE",Q81="MODERATELY_ENGAGED"), "HIGH", IF(AND(L81="NORMAL",M81="MEDIUM",O81="MODERATE-WAIT",P81="MEDIUM_PRESSURE",Q81="MODERATELY_ENGAGED"), "MEDIUM", "LOW"))) -> LOW
A82: 104 | B82: No | C82: 30 | D82: Research & Development | E82: Laboratory Technician | F82: 5126 | G82: Yes | H82: 10 | I82: 3 | J82: 4 | K82: 2 | L82: =IF(AND(G82="YES",J82<=2,I82>=3),"HIGH RISK","NORMAL") -> NORMAL | M82: =IF(F82<=4000,"LOW",IF(F82>9000,"MEDIUM","HIGH")) -> HIGH | N82: =IF(H82<=2,"NEW",IF(H82<=6,"MID","SENIOR")) -> SENIOR | O82: =IF(I82<=1,"RECENTLY PROMOTED",IF(I82<=3,"MODERATE-WAIT","STAGNANT")) -> MODERATE-WAIT | P82: =IF(AND(G82="Yes",K82<=2),"High_Pressure", IF(OR(G82="Yes",K82=3),"Medium_Pressure", "Low_Pressure")) -> High_Pressure | Q82: =IF(AND(J82>=3,K82>=3,L82>=3), "HIGHLY_ENGAGED", IF(OR(J82<=2,K82<=2,L82<=2), "DISENGAGED", "MODERATELY_ENGAGED")) -> DISENGAGED | R82: =IF(AND(L82="HIGH",O82="STAGNANT",P82="HIGH_PRESSURE",Q82="DISENGAGED"), "CRITICAL", IF(AND(L82="HIGH",M82="LOW",P82="HIGH_PRESSURE",Q82="MODERATELY_ENGAGED"), "HIGH", IF(AND(L82="NORMAL",M82="MEDIUM",O82="MODERATE-WAIT",P82="MEDIUM_PRESSURE",Q82="MODERATELY_ENGAGED"), "MEDIUM", "LOW"))) -> LOW
A83: 105 | B83: No | C83: 35 | D83: Research & Development | E83: Research Scientist | F83: 2859 | G83: No | H83: 6 | I83: 0 | J83: 3 | K83: 3 | L83: =IF(AND(G83="YES",J83<=2,I83>=3),"HIGH RISK","NORMAL") -> NORMAL | M83: =IF(F83<=4000,"LOW",IF(F83>9000,"MEDIUM","HIGH")) -> LOW | N83: =IF(H83<=2,"NEW",IF(H83<=6,"MID","SENIOR")) -> MID | O83: =IF(I83<=1,"RECENTLY PROMOTED",IF(I83<=3,"MODERATE-WAIT","STAGNANT")) -> RECENTLY PROMOTED | P83: =IF(AND(G83="Yes",K83<=2),"High_Pressure", IF(OR(G83="Yes",K83=3),"Medium_Pressure", "Low_Pressure")) -> Medium_Pressure | Q83: =IF(AND(J83>=3,K83>=3,L83>=3), "HIGHLY_ENGAGED", IF(OR(J83<=2,K83<=2,L83<=2), "DISENGAGED", "MODERATELY_ENGAGED")) -> HIGHLY_ENGAGED | R83: =IF(AND(L83="HIGH",O83="STAGNANT",P83="HIGH_PRESSURE",Q83="DISENGAGED"), "CRITICAL", IF(AND(L83="HIGH",M83="LOW",P83="HIGH_PRESSURE",Q83="MODERATELY_ENGAGED"), "HIGH", IF(AND(L83="NORMAL",M83="MEDIUM",O83="MODERATE-WAIT",P83="MEDIUM_PRESSURE",Q83="MODERATELY_ENGAGED"), "MEDIUM", "LOW"))) -> LOW
A84: 106 | B84: No | C84: 55 | D84: Sales | E84: Sales Executive | F84: 10239 | G84: No | H84: 1 | I84: 1 | J84: 4 | K84: 3 | L84: =IF(AND(G84="YES",J84<=2,I84>=3),"HIGH RISK","NORMAL") -> NORMAL | M84: =IF(F84<=4000,"LOW",IF(F84>9000,"MEDIUM","HIGH")) -> MEDIUM | N84: =IF(H84<=2,"NEW",IF(H84<=6,"MID","SENIOR")) -> NEW | O84: =IF(I84<=1,"RECENTLY PROMOTED",IF(I84<=3,"MODERATE-WAIT","STAGNANT")) -> RECENTLY PROMOTED | P84: =IF(AND(G84="Yes",K84<=2),"High_Pressure", IF(OR(G84="Yes",K84=3),"Medium_Pressure", "Low_Pressure")) -> Medium_Pressure | Q84: =IF(AND(J84>=3,K84>=3,L84>=3), "HIGHLY_ENGAGED", IF(OR(J84<=2,K84<=2,L84<=2), "DISENGAGED", "MODERATELY_ENGAGED")) -> HIGHLY_ENGAGED | R84: =IF(AND(L84="HIGH",O84="STAGNANT",P84="HIGH_PRESSURE",Q84="DISENGAGED"), "CRITICAL", IF(AND(L84="HIGH",M84="LOW",P84="HIGH_PRESSURE",Q84="MODERATELY_ENGAGED"), "HIGH", IF(AND(L84="NORMAL",M84="MEDIUM",O84="MODERATE-WAIT",P84="MEDIUM_PRESSURE",Q84="MODERATELY_ENGAGED"), "MEDIUM", "LOW"))) -> LOW
A85: 107 | B85: No | C85: 38 | D85: Research & Development | E85: Research Scientist | F85: 5329 | G85: Yes | H85: 13 | I85: 1 | J85: 4 | K85: 3 | L85: =IF(AND(G85="YES",J85<=2,I85>=3),"HIGH RISK","NORMAL") -> NORMAL | M85: =IF(F85<=4000,"LOW",IF(F85>9000,"MEDIUM","HIGH")) -> HIGH | N85: =IF(H85<=2,"NEW",IF(H85<=6,"MID","SENIOR")) -> SENIOR | O85: =IF(I85<=1,"RECENTLY PROMOTED",IF(I85<=3,"MODERATE-WAIT","STAGNANT")) -> RECENTLY PROMOTED | P85: =IF(AND(G85="Yes",K85<=2),"High_Pressure", IF(OR(G85="Yes",K85=3),"Medium_Pressure", "Low_Pressure")) -> Medium_Pressure | Q85: =IF(AND(J85>=3,K85>=3,L85>=3), "HIGHLY_ENGAGED", IF(OR(J85<=2,K85<=2,L85<=2), "DISENGAGED", "MODERATELY_ENGAGED")) -> HIGHLY_ENGAGED | R85: =IF(AND(L85="HIGH",O85="STAGNANT",P85="HIGH_PRESSURE",Q85="DISENGAGED"), "CRITICAL", IF(AND(L85="HIGH",M85="LOW",P85="HIGH_PRESSURE",Q85="MODERATELY_ENGAGED"), "HIGH", IF(AND(L85="NORMAL",M85="MEDIUM",O85="MODERATE-WAIT",P85="MEDIUM_PRESSURE",Q85="MODERATELY_ENGAGED"), "MEDIUM", "LOW"))) -> LOW
A86: 110 | B86: No | C86: 34 | D86: Research & Development | E86: Manufacturing Director | F86: 4325 | G86: No | H86: 5 | I86: 1 | J86: 2 | K86: 3 | L86: =IF(AND(G86="YES",J86<=2,I86>=3),"HIGH RISK","NORMAL") -> NORMAL | M86: =IF(F86<=4000,"LOW",IF(F86>9000,"MEDIUM","HIGH")) -> HIGH | N86: =IF(H86<=2,"NEW",IF(H86<=6,"MID","SENIOR")) -> MID | O86: =IF(I86<=1,"RECENTLY PROMOTED",IF(I86<=3,"MODERATE-WAIT","STAGNANT")) -> RECENTLY PROMOTED | P86: =IF(AND(G86="Yes",K86<=2),"High_Pressure", IF(OR(G86="Yes",K86=3),"Medium_Pressure", "Low_Pressure")) -> Medium_Pressure | Q86: =IF(AND(J86>=3,K86>=3,L86>=3), "HIGHLY_ENGAGED", IF(OR(J86<=2,K86<=2,L86<=2), "DISENGAGED", "MODERATELY_ENGAGED")) -> DISENGAGED | R86: =IF(AND(L86="HIGH",O86="STAGNANT",P86="HIGH_PRESSURE",Q86="DISENGAGED"), "CRITICAL", IF(AND(L86="HIGH",M86="LOW",P86="HIGH_PRESSURE",Q86="MODERATELY_ENGAGED"), "HIGH", IF(AND(L86="NORMAL",M86="MEDIUM",O86="MODERATE-WAIT",P86="MEDIUM_PRESSURE",Q86="MODERATELY_ENGAGED"), "MEDIUM", "LOW"))) -> LOW
... A1471: 2068 | B1471: No | C1471: 34 | D1471: Research & Development | E1471: Laboratory Technician | F1471: 4404 | G1471: No | H1471: 4 | I1471: 1 | J1471: 3 | K1471: 4 | L1471: =IF(AND(G1471="YES",J1471<=2,I1471>=3),"HIGH RISK","NORMAL") -> NORMAL | M1471: =IF(F1471<=4000,"LOW",IF(F1471>9000,"MEDIUM","HIGH")) -> HIGH | N1471: =IF(H1471<=2,"NEW",IF(H1471<=6,"MID","SENIOR")) -> MID | O1471: =IF(I1471<=1,"RECENTLY PROMOTED",IF(I1471<=3,"MODERATE-WAIT","STAGNANT")) -> RECENTLY PROMOTED | P1471: =IF(AND(G1471="Yes",K1471<=2),"High_Pressure", IF(OR(G1471="Yes",K1471=3),"Medium_Pressure", "Low_Pressure")) -> Low_Pressure | Q1471: =IF(AND(J1471>=3,K1471>=3,L1471>=3), "HIGHLY_ENGAGED", IF(OR(J1471<=2,K1471<=2,L1471<=2), "DISENGAGED", "MODERATELY_ENGAGED")) -> HIGHLY_ENGAGED | R1471: =IF(AND(L1471="HIGH",O1471="STAGNANT",P1471="HIGH_PRESSURE",Q1471="DISENGAGED"), "CRITICAL", IF(AND(L1471="HIGH",M1471="LOW",P1471="HIGH_PRESSURE",Q1471="MODERATELY_ENGAGED"), "HIGH", IF(AND(L1471="NORMAL",M1471="MEDIUM",O1471="MODERATE-WAIT",P1471="MEDIUM_PRESSURE",Q1471="MODERATELY_ENGAGED"), "MEDIUM", "LOW"))) -> LOW

Sheet SEGMENTS
A1: EMPLOYEMENT NUMBER | B1: DEPARTMENT | C1: HIGH ATTRITION RISK | D1: RETENTION PRIORITY | E1: ENGAGEMENT LEVEL | F1: WORK PRESSURE LEVEL | G1: INCOME LEVEL GROUP | H1: PROMOTION STAGNATION | I1: SEGMENT LEVEL
A2: 1 | B2: Sales | C2: =FEATURES!L2 -> NORMAL | D2: =FEATURES!R2 -> LOW | E2: =FEATURES!Q2 -> DISENGAGED | F2: =FEATURES!P2 -> High_Pressure | G2: =FEATURES!M2 -> HIGH | H2: =FEATURES!O2 -> RECENTLY PROMOTED | I2: =IF(AND(C2="HIGH",D2="HIGH",E2="DISENGAGED",F2="HIGH_PRESSURE",G2="LOW",H2="STAGNANT"),"HIGH RISK",IF(AND(C2="NORMAL",D2="MEDIUM",E2="MODERATELY ENGAGED",G2="MEDIUM",H2="MODERATE WAIT"),"MEDIUM RISK", "LOW RISK")) -> LOW RISK
A3: 2 | B3: Research & Development | C3: =FEATURES!L3 -> NORMAL | D3: =FEATURES!R3 -> LOW | E3: =FEATURES!Q3 -> DISENGAGED | F3: =FEATURES!P3 -> Medium_Pressure | G3: =FEATURES!M3 -> HIGH | H3: =FEATURES!O3 -> RECENTLY PROMOTED | I3: =IF(AND(C3="HIGH",D3="HIGH",E3="DISENGAGED",F3="HIGH_PRESSURE",G3="LOW",H3="STAGNANT"),"HIGH RISK",IF(AND(C3="NORMAL",D3="MEDIUM",E3="MODERATELY ENGAGED",G3="MEDIUM",H3="MODERATE WAIT"),"MEDIUM RISK", "LOW RISK")) -> LOW RISK
A4: 4 | B4: Research & Development | C4: =FEATURES!L4 -> NORMAL | D4: =FEATURES!R4 -> LOW | E4: =FEATURES!Q4 -> HIGHLY_ENGAGED | F4: =FEATURES!P4 -> Medium_Pressure | G4: =FEATURES!M4 -> LOW | H4: =FEATURES!O4 -> RECENTLY PROMOTED | I4: =IF(AND(C4="HIGH",D4="HIGH",E4="DISENGAGED",F4="HIGH_PRESSURE",G4="LOW",H4="STAGNANT"),"HIGH RISK",IF(AND(C4="NORMAL",D4="MEDIUM",E4="MODERATELY ENGAGED",G4="MEDIUM",H4="MODERATE WAIT"),"MEDIUM RISK", "LOW RISK")) -> LOW RISK
A5: 5 | B5: Research & Development | C5: =FEATURES!L5 -> NORMAL | D5: =FEATURES!R5 -> LOW | E5: =FEATURES!Q5 -> HIGHLY_ENGAGED | F5: =FEATURES!P5 -> Medium_Pressure | G5: =FEATURES!M5 -> LOW | H5: =FEATURES!O5 -> MODERATE-WAIT | I5: =IF(AND(C5="HIGH",D5="HIGH",E5="DISENGAGED",F5="HIGH_PRESSURE",G5="LOW",H5="STAGNANT"),"HIGH RISK",IF(AND(C5="NORMAL",D5="MEDIUM",E5="MODERATELY ENGAGED",G5="MEDIUM",H5="MODERATE WAIT"),"MEDIUM RISK", "LOW RISK")) -> LOW RISK
A6: 7 | B6: Research & Development | C6: =FEATURES!L6 -> NORMAL | D6: =FEATURES!R6 -> LOW | E6: =FEATURES!Q6 -> DISENGAGED | F6: =FEATURES!P6 -> Medium_Pressure | G6: =FEATURES!M6 -> LOW | H6: =FEATURES!O6 -> MODERATE-WAIT | I6: =IF(AND(C6="HIGH",D6="HIGH",E6="DISENGAGED",F6="HIGH_PRESSURE",G6="LOW",H6="STAGNANT"),"HIGH RISK",IF(AND(C6="NORMAL",D6="MEDIUM",E6="MODERATELY ENGAGED",G6="MEDIUM",H6="MODERATE WAIT"),"MEDIUM RISK", "LOW RISK")) -> LOW RISK
A7: 8 | B7: Research & Development | C7: =FEATURES!L7 -> NORMAL | D7: =FEATURES!R7 -> LOW | E7: =FEATURES!Q7 -> DISENGAGED | F7: =FEATURES!P7 -> Low_Pressure | G7: =FEATURES!M7 -> LOW | H7: =FEATURES!O7 -> MODERATE-WAIT | I7: =IF(AND(C7="HIGH",D7="HIGH",E7="DISENGAGED",F7="HIGH_PRESSURE",G7="LOW",H7="STAGNANT"),"HIGH RISK",IF(AND(C7="NORMAL",D7="MEDIUM",E7="MODERATELY ENGAGED",G7="MEDIUM",H7="MODERATE WAIT"),"MEDIUM RISK", "LOW RISK")) -> LOW RISK
A8: 10 | B8: Research & Development | C8: =FEATURES!L8 -> NORMAL | D8: =FEATURES!R8 -> LOW | E8: =FEATURES!Q8 -> DISENGAGED | F8: =FEATURES!P8 -> High_Pressure | G8: =FEATURES!M8 -> LOW | H8: =FEATURES!O8 -> RECENTLY PROMOTED | I8: =IF(AND(C8="HIGH",D8="HIGH",E8="DISENGAGED",F8="HIGH_PRESSURE",G8="LOW",H8="STAGNANT"),"HIGH RISK",IF(AND(C8="NORMAL",D8="MEDIUM",E8="MODERATELY ENGAGED",G8="MEDIUM",H8="MODERATE WAIT"),"MEDIUM RISK", "LOW RISK")) -> LOW RISK
A9: 11 | B9: Research & Development | C9: =FEATURES!L9 -> NORMAL | D9: =FEATURES!R9 -> LOW | E9: =FEATURES!Q9 -> HIGHLY_ENGAGED | F9: =FEATURES!P9 -> Medium_Pressure | G9: =FEATURES!M9 -> LOW | H9: =FEATURES!O9 -> RECENTLY PROMOTED | I9: =IF(AND(C9="HIGH",D9="HIGH",E9="DISENGAGED",F9="HIGH_PRESSURE",G9="LOW",H9="STAGNANT"),"HIGH RISK",IF(AND(C9="NORMAL",D9="MEDIUM",E9="MODERATELY ENGAGED",G9="MEDIUM",H9="MODERATE WAIT"),"MEDIUM RISK", "LOW RISK")) -> LOW RISK
A10: 12 | B10: Research & Development | C10: =FEATURES!L10 -> NORMAL | D10: =FEATURES!R10 -> LOW | E10: =FEATURES!Q10 -> HIGHLY_ENGAGED | F10: =FEATURES!P10 -> Medium_Pressure | G10: =FEATURES!M10 -> MEDIUM | H10: =FEATURES!O10 -> RECENTLY PROMOTED | I10: =IF(AND(C10="HIGH",D10="HIGH",E10="DISENGAGED",F10="HIGH_PRESSURE",G10="LOW",H10="STAGNANT"),"HIGH RISK",IF(AND(C10="NORMAL",D10="MEDIUM",E10="MODERATELY ENGAGED",G10="MEDIUM",H10="MODERATE WAIT"),"MEDIUM RISK", "LOW RISK")) -> LOW RISK
A11: 13 | B11: Research & Development | C11: =FEATURES!L11 -> NORMAL | D11: =FEATURES!R11 -> LOW | E11: =FEATURES!Q11 -> DISENGAGED | F11: =FEATURES!P11 -> Low_Pressure | G11: =FEATURES!M11 -> HIGH | H11: =FEATURES!O11 -> STAGNANT | I11: =IF(AND(C11="HIGH",D11="HIGH",E11="DISENGAGED",F11="HIGH_PRESSURE",G11="LOW",H11="STAGNANT"),"HIGH RISK",IF(AND(C11="NORMAL",D11="MEDIUM",E11="MODERATELY ENGAGED",G11="MEDIUM",H11="MODERATE WAIT"),"MEDIUM RISK", "LOW RISK")) -> LOW RISK
A12: 14 | B12: Research & Development | C12: =FEATURES!L12 -> NORMAL | D12: =FEATURES!R12 -> LOW | E12: =FEATURES!Q12 -> DISENGAGED | F12: =FEATURES!P12 -> Medium_Pressure | G12: =FEATURES!M12 -> LOW | H12: =FEATURES!O12 -> RECENTLY PROMOTED | I12: =IF(AND(C12="HIGH",D12="HIGH",E12="DISENGAGED",F12="HIGH_PRESSURE",G12="LOW",H12="STAGNANT"),"HIGH RISK",IF(AND(C12="NORMAL",D12="MEDIUM",E12="MODERATELY ENGAGED",G12="MEDIUM",H12="MODERATE WAIT"),"MEDIUM RISK", "LOW RISK")) -> LOW RISK
A13: 15 | B13: Research & Development | C13: =FEATURES!L13 -> NORMAL | D13: =FEATURES!R13 -> LOW | E13: =FEATURES!Q13 -> HIGHLY_ENGAGED | F13: =FEATURES!P13 -> Medium_Pressure | G13: =FEATURES!M13 -> HIGH | H13: =FEATURES!O13 -> RECENTLY PROMOTED | I13: =IF(AND(C13="HIGH",D13="HIGH",E13="DISENGAGED",F13="HIGH_PRESSURE",G13="LOW",H13="STAGNANT"),"HIGH RISK",IF(AND(C13="NORMAL",D13="MEDIUM",E13="MODERATELY ENGAGED",G13="MEDIUM",H13="MODERATE WAIT"),"MEDIUM RISK", "LOW RISK")) -> LOW RISK
... A1471: 2068 | B1471: Research & Development | C1471: =FEATURES!L1471 -> NORMAL | D1471: =FEATURES!R1471 -> LOW | E1471: =FEATURES!Q1471 -> HIGHLY_ENGAGED | F1471: =FEATURES!P1471 -> Low_Pressure | G1471: =FEATURES!M1471 -> HIGH | H1471: =FEATURES!O1471 -> RECENTLY PROMOTED | I1471: =IF(AND(C1471="HIGH",D1471="HIGH",E1471="DISENGAGED",F1471="HIGH_PRESSURE",G1471="LOW",H1471="STAGNANT"),"HIGH RISK",IF(AND(C1471="NORMAL",D1471="MEDIUM",E1471="MODERATELY ENGAGED",G1471="MEDIUM",H1471="MODERATE WAIT"),"MEDIUM RISK", "LOW RISK")) -> LOW RISK

Sheet DATA MODEL
A1: ENTITIY NAME | B1: DESCRIPTION | C1: TABLE NAME | D1: PRIMARY KEY | E1: MAIN COLUMNS | F1: RELATIONSHIP
A2: EMPLOYEE | B2: BASIC EMPLOYEE IDENTITY | C2: EMPLOYEE | D2: EMPLOYEE NUMBER | E2: EMPLOYEE NUMBERS,AGE ,GENDER, MARTIAL STATUS,EDUCATION, EDUCATION FIELD | F2: MASTER TABLE
A3: JOB | B3: JOB ROLE, LEVEL,DEPARTMENT | C3: JOB | D3: JOB_ID | E3: JOB ID, EMPLOYEE NUMBER(FK),DEPARTMENT,JOB ROLE, JOB LEVEL, BUSINNES LEVEL, OVERTIME | F3: JOB.EMPLOYEE_NUMBER→EMPLOYEE.EMPLOYEE_NUMBER
A4: COMPENSATION | B4: SALARY AND PAY DATA | C4: COMPENSATION | E4: COMP_ID,EMPLOYEE NUMBER(FK),MONTHLY INCOME,DAILY_RATE,HOURLY_RATE,PERCENT_SALARY_HIKE | F4: COMPENSATION.EMPLOYEE_NUMBER→ EMPLOYEE.EMPLOYEE_NUMBER
A5: PERFORMANCE | B5: RATING , HIKES | C5: PERFORMANCE | D5: PERF_ID | E5: PERF_ID,EMPLOYEE_NUMBER(FK),PERFORMANCE_RATIG,TRAINING_TIME_LAST_YEAR | F5: PERFORMANCE.EMPLOYEE_NUMBER→ EMPLOYEE.EMPLOYEE_NUMBER
A6: SATISFACTION | B6: ENGAGEMENT, SATISFACTION DATA | C6: SATISFACTION | D6: SAT_ID | E6: SAT-ID, EMPLOYEE_NUMBER(FK), JOB_SATISFACTION, RELATIONSHIP_SATISFACTION, WORK_LIFE_BALANCE | F6: SATISFACTION.EMPLOYEE_NUMBER→ EMPLYEE.EMPLOYEE_NUMBER
A7: EXPERIENCE | B7: TIME, TENURE , PROMOTION HISTORY | C7: EXPERIENCE | D7: EXP_ID | E7: EXP_ID, EMPLOYEE_NUMBER(FK), YEARS_AT_COMPANY,YEARS_IN_CURRENT_ROLE,YEARS_SINCE_LAST_PERFORMANCE, TOTAL_WORKING_YEARS | F7: EXPERIENCE..EMPLOYEE_NUMBER→ EMPLOYEE.EMPLOYEE_NUMBER
